{
  "$schema": "https://raw.githubusercontent.com/devcontainers/spec/main/schemas/devContainer.schema.json",
  "name": "ContainerForge",
  "image": "oci.trueforge.org/containerforge/devcontainer:4.1.1@sha256:a37275a4c9d7bafa7752bb9eface12627b5b32e98f59fcdfca618e813882600e",
  "postStartCommand": "git config --global --add safe.directory ${containerWorkspaceFolder}",
  "features": {
    "ghcr.io/devcontainers/features/docker-outside-of-docker:1": {"moby": false}
  },
  "customizations": {
    "vscode": {
      "extensions": [
        "mitchdenny.ecdc",
        "EditorConfig.editorconfig",
        "PKief.material-icon-theme",
        "usernamehw.errorlens",
        "redhat.vscode-yaml",
        "ms-azuretools.vscode-docker",
        "hashicorp.hcl",
        "exiasr.hadolint",
        "golang.go",
        "joao-peterson.gotag",
        "eamodio.gitlens",
        "timonwong.shellcheck",
        "formulahendry.code-runner",
        "streetsidesoftware.code-spell-checker",
        "mhutchie.git-graph",
        "yzhang.markdown-all-in-one",
        "searKing.preview-vscode",
        "DavidAnson.vscode-markdownlint",
        "GitHub.copilot"
      ]
    }
  }
}
