{
  "$schema": "https://raw.githubusercontent.com/devcontainers/spec/main/schemas/devContainer.schema.json",
  "name": "ContainerForge",
  "image": "oci.trueforge.org/containerforge/devcontainer:3.0.2@sha256:0a050ac12fd402ea0697460f18831edc21067f1b7b16913cc6e6732b264c20f9",
  "postStartCommand": "git config --global --add safe.directory ${containerWorkspaceFolder}",
  "customizations": {
    "vscode": {
      "extensions": [
        "mitchdenny.ecdc",
        "EditorConfig.editorconfig",
        "PKief.material-icon-theme",
        "usernamehw.errorlens",
        "redhat.vscode-yaml",
        "ms-azuretools.vscode-docker",
        "hashicorp.hcl",
        "exiasr.hadolint",
        "golang.go",
        "joao-peterson.gotag",
        "eamodio.gitlens",
        "timonwong.shellcheck",
        "formulahendry.code-runner",
        "streetsidesoftware.code-spell-checker",
        "Codium.codium",
        "mhutchie.git-graph",
        "yzhang.markdown-all-in-one",
        "searKing.preview-vscode",
        "DavidAnson.vscode-markdownlint",
        "GitHub.copilot"
      ]
    }
  }
}
